simple_latex_checker/__init__.py
simple_latex_checker/latex_check.py
simple_latex_checker-0.0.10.dist-info/METADATA
simple_latex_checker-0.0.10.dist-info/WHEEL
simple_latex_checker-0.0.10.dist-info/licenses/LICENSE
simple_latex_checker-0.0.10.dist-info/RECORD
