Metadata-Version: 2.3
Name: simple_latex_checker
Version: 0.0.10
Summary: VERY simple and lightweight checking of latex formatting
Project-URL: Homepage, https://github.com/vincedbowen/simple-latex-checker
Project-URL: Issues, https://github.com/vincedbowen/simple-latex-checker/issues
Author-email: Vincent Bowen <vincent@vincentbowen.com>
License-File: LICENSE
Classifier: License :: OSI Approved :: Mozilla Public License 2.0 (MPL 2.0)
Classifier: Operating System :: OS Independent
Classifier: Programming Language :: Python :: 3
Requires-Python: >=3.8
